starfield/__init__.py
starfield/__init__.pyi
starfield/py.typed
starfield-0.3.2.dist-info/WHEEL
starfield-0.3.2.dist-info/METADATA
starfield-0.3.2.dist-info/RECORD
