Metadata-Version: 2.1
Name: starfield
Version: 0.3.2
Summary: 
Author: IsaacBreen
Author-email: 57783927+IsaacBreen@users.noreply.github.com
Requires-Python: >=3.9,<4.0
Classifier: Programming Language :: Python :: 3
Classifier: Programming Language :: Python :: 3.9
Classifier: Programming Language :: Python :: 3.10
Classifier: Programming Language :: Python :: 3.11
Requires-Dist: attrs (>=22.2.0,<23.0.0)
